{"__type__":"dragonBones.DragonBonesAtlasAsset","_name":"kaishi_tex","_atlasJson":"{\"name\":\"kaishi\",\"imagePath\":\"kaishi_tex.png\",\"SubTexture\":[{\"width\":976,\"y\":747,\"height\":179,\"name\":\"zuo\",\"x\":1},{\"width\":1088,\"y\":568,\"height\":177,\"name\":\"you\",\"x\":1},{\"width\":496,\"y\":1,\"height\":565,\"name\":\"shandian\",\"x\":1},{\"width\":137,\"y\":747,\"height\":137,\"name\":\"kai\",\"x\":1123},{\"width\":142,\"y\":747,\"height\":143,\"name\":\"shi\",\"x\":979}]}","texture":{"__uuid__":"desC9dhntP8LsYNcBj8YiZ"}}